agrirouter/__init__.py
agrirouter/api/__init__.py
agrirouter/api/constants.py
agrirouter/api/enums.py
agrirouter/api/env.py
agrirouter/api/exceptions.py
agrirouter/api/messages.py
agrirouter/api/messaging_builders.py
agrirouter/generated/__init__.py
agrirouter/generated/cloud_provider_integration/__init__.py
agrirouter/generated/cloud_provider_integration/cloud_virtualized_app_registration_pb2.py
agrirouter/generated/commons/__init__.py
agrirouter/generated/commons/chunk_pb2.py
agrirouter/generated/commons/message_pb2.py
agrirouter/generated/messaging/__init__.py
agrirouter/generated/messaging/request/__init__.py
agrirouter/generated/messaging/request/request_pb2.py
agrirouter/generated/messaging/request/payload/__init__.py
agrirouter/generated/messaging/request/payload/account/__init__.py
agrirouter/generated/messaging/request/payload/account/endpoints_pb2.py
agrirouter/generated/messaging/request/payload/efdi/__init__.py
agrirouter/generated/messaging/request/payload/efdi/efdi_pb2.py
agrirouter/generated/messaging/request/payload/endpoint/__init__.py
agrirouter/generated/messaging/request/payload/endpoint/capabilities_pb2.py
agrirouter/generated/messaging/request/payload/endpoint/subscription_pb2.py
agrirouter/generated/messaging/request/payload/feed/__init__.py
agrirouter/generated/messaging/request/payload/feed/feed_requests_pb2.py
agrirouter/generated/messaging/request/payload/gps/__init__.py
agrirouter/generated/messaging/request/payload/gps/gps_pb2.py
agrirouter/generated/messaging/response/__init__.py
agrirouter/generated/messaging/response/response_pb2.py
agrirouter/generated/messaging/response/payload/__init__.py
agrirouter/generated/messaging/response/payload/account/__init__.py
agrirouter/generated/messaging/response/payload/account/endpoints_pb2.py
agrirouter/generated/messaging/response/payload/endpoint/__init__.py
agrirouter/generated/messaging/response/payload/endpoint/capability_pb2.py
agrirouter-2.1.0a1.dist-info/LICENSE
agrirouter-2.1.0a1.dist-info/METADATA
agrirouter-2.1.0a1.dist-info/WHEEL
agrirouter-2.1.0a1.dist-info/top_level.txt
agrirouter-2.1.0a1.dist-info/RECORD
