Metadata-Version: 2.1
Name: agrirouter
Version: 2.1.0a1
Summary: Python SDK for the agrirouter API. This project contains the API for the communication with the agrirouter. Everything you need for the onboarding process, secure communication and much more.
Author-email: Alexey Petrovsky <petrovsky.lexey@gmail.com>, Oliver Rahner <o.rahner@dke-data.com>, Sascha Dömer <Cf4ThQgxcnxAovOUXTNv@saschadoemer.de>
Project-URL: Source, https://github.com/DKE-Data/agrirouter-sdk-python
Classifier: Intended Audience :: Developers
Classifier: License :: OSI Approved :: Apache Software License
Classifier: Programming Language :: Python :: 3.7
Classifier: Programming Language :: Python :: 3.8
Classifier: Programming Language :: Python :: 3.9
Classifier: Programming Language :: Python :: 3.10
Classifier: Programming Language :: Python :: 3.11
Classifier: Programming Language :: Python :: 3.12
Classifier: Topic :: Software Development :: Libraries
Classifier: Topic :: Software Development :: Libraries :: Python Modules
Requires-Python: >=3.7
License-File: LICENSE
Requires-Dist: requests
Requires-Dist: protobuf ~=3.18.0
